worldex/__init__.py
worldex-0.0.1a0.dist-info/METADATA
worldex-0.0.1a0.dist-info/WHEEL
worldex-0.0.1a0.dist-info/RECORD
