Metadata-Version: 2.1
Name: worldex
Version: 0.0.1a0
Summary: Solutions for building geographic indices for indexing the world.
Home-page: https://www.github.com/avsolatorio/worldex
License: MIT
Author: Aivin V. Solatorio
Author-email: avsolatorio@gmail.com
Classifier: License :: OSI Approved :: MIT License
Classifier: Programming Language :: Python :: 2
Classifier: Programming Language :: Python :: 2.7
Classifier: Programming Language :: Python :: 3
Classifier: Programming Language :: Python :: 3.4
Classifier: Programming Language :: Python :: 3.5
Classifier: Programming Language :: Python :: 3.6
Classifier: Programming Language :: Python :: 3.7
Classifier: Programming Language :: Python :: 3.8
Classifier: Programming Language :: Python :: 3.9
Classifier: Programming Language :: Python :: 3.10
Classifier: Programming Language :: Python :: 3.11
Project-URL: Repository, https://www.github.com/avsolatorio/worldex
